tldr_news/__init__.py
tldr_news/cli.py
tldr_news/main.css
tldr_news/ui.py
tldr_news/utils.py
tldr_news-0.2.12.dist-info/METADATA
tldr_news-0.2.12.dist-info/WHEEL
tldr_news-0.2.12.dist-info/entry_points.txt
tldr_news-0.2.12.dist-info/RECORD
