Metadata-Version: 2.1
Name: tldr-news
Version: 0.2.12
Summary: 
Author: Harry Tran
Author-email: huytran.quang080199@gmail.com
Requires-Python: >=3.10,<4.0
Classifier: Programming Language :: Python :: 3
Classifier: Programming Language :: Python :: 3.10
Classifier: Programming Language :: Python :: 3.11
Classifier: Programming Language :: Python :: 3.12
Requires-Dist: beautifulsoup4 (>=4.11.2,<5.0.0)
Requires-Dist: click (>=8.1.3,<9.0.0)
Requires-Dist: requests (>=2.32.0,<3.0.0)
Requires-Dist: textual (>=0.15.1,<0.16.0)
